dbgpt_ext/__init__.py
dbgpt_ext/_version.py
dbgpt_ext/datasource/__init__.py
dbgpt_ext/datasource/conn_spark.py
dbgpt_ext/datasource/conn_tugraph.py
dbgpt_ext/datasource/redis.py
dbgpt_ext/datasource/schema.py
dbgpt_ext/datasource/nosql/__init__.py
dbgpt_ext/datasource/rdbms/__init__.py
dbgpt_ext/datasource/rdbms/conn_clickhouse.py
dbgpt_ext/datasource/rdbms/conn_doris.py
dbgpt_ext/datasource/rdbms/conn_duckdb.py
dbgpt_ext/datasource/rdbms/conn_gaussdb.py
dbgpt_ext/datasource/rdbms/conn_hive.py
dbgpt_ext/datasource/rdbms/conn_mssql.py
dbgpt_ext/datasource/rdbms/conn_mysql.py
dbgpt_ext/datasource/rdbms/conn_oceanbase.py
dbgpt_ext/datasource/rdbms/conn_oracle.py
dbgpt_ext/datasource/rdbms/conn_postgresql.py
dbgpt_ext/datasource/rdbms/conn_sqlite.py
dbgpt_ext/datasource/rdbms/conn_starrocks.py
dbgpt_ext/datasource/rdbms/conn_vertica.py
dbgpt_ext/datasource/rdbms/dialect/__init__.py
dbgpt_ext/datasource/rdbms/dialect/oceanbase/__init__.py
dbgpt_ext/datasource/rdbms/dialect/oceanbase/ob_dialect.py
dbgpt_ext/datasource/rdbms/dialect/starrocks/__init__.py
dbgpt_ext/datasource/rdbms/dialect/starrocks/sqlalchemy/__init__.py
dbgpt_ext/datasource/rdbms/dialect/starrocks/sqlalchemy/datatype.py
dbgpt_ext/datasource/rdbms/dialect/starrocks/sqlalchemy/dialect.py
dbgpt_ext/datasource/rdbms/dialect/vertica/__init__.py
dbgpt_ext/datasource/rdbms/dialect/vertica/base.py
dbgpt_ext/datasource/rdbms/dialect/vertica/dialect_vertica_python.py
dbgpt_ext/llms/__init__.py
dbgpt_ext/rag/__init__.py
dbgpt_ext/rag/chunk_manager.py
dbgpt_ext/rag/assembler/__init__.py
dbgpt_ext/rag/assembler/base.py
dbgpt_ext/rag/assembler/bm25.py
dbgpt_ext/rag/assembler/db_schema.py
dbgpt_ext/rag/assembler/embedding.py
dbgpt_ext/rag/assembler/summary.py
dbgpt_ext/rag/embeddings/__init__.py
dbgpt_ext/rag/embeddings/aimlapi.py
dbgpt_ext/rag/embeddings/jina.py
dbgpt_ext/rag/embeddings/ollama.py
dbgpt_ext/rag/embeddings/qianfan.py
dbgpt_ext/rag/embeddings/siliconflow.py
dbgpt_ext/rag/embeddings/tongyi.py
dbgpt_ext-0.7.4.dist-info/METADATA
dbgpt_ext-0.7.4.dist-info/WHEEL
dbgpt_ext-0.7.4.dist-info/RECORD
